kafa/VERSION
kafa/__init__.py
kafa/config.py
kafa/errors.py
kafa/_source/__init__.py
kafa/_source/consumer.py
kafa/_source/producer.py
kafa/_source/topic.py
kafa-0.1.2.dist-info/LICENSE
kafa-0.1.2.dist-info/METADATA
kafa-0.1.2.dist-info/WHEEL
kafa-0.1.2.dist-info/top_level.txt
kafa-0.1.2.dist-info/RECORD
