Metadata-Version: 2.1
Name: kafa
Version: 0.1.2
Summary: A python library to easily create kafka producer and consumer
Author-email: Yan Zhang <dev.claude.yan.zhang@gmail.com>
License: GNU GENERAL PUBLIC LICENSE
Project-URL: Homepage, https://github.com/Claudezss/PyKafka
Project-URL: Bug Tracker, https://github.com/Claudezss/PyKafka/issues
Keywords: kafka
Classifier: Development Status :: 3 - Alpha
Classifier: Programming Language :: Python :: 3
Classifier: License :: OSI Approved :: GNU General Public License (GPL)
Classifier: Operating System :: OS Independent
Classifier: Topic :: Software Development :: Libraries
Requires-Python: >=3.7
License-File: LICENSE
